ampq_websockets/__init__.py
ampq_websockets/_clients.py
ampq_websockets/_runserver.py
ampq_websockets/_settings.py
ampq_websockets/_subscribe.py
ampq_websockets/_token.py
py_ampq_websocket_server-0.1.7.dist-info/LICENSE
py_ampq_websocket_server-0.1.7.dist-info/METADATA
py_ampq_websocket_server-0.1.7.dist-info/WHEEL
py_ampq_websocket_server-0.1.7.dist-info/top_level.txt
py_ampq_websocket_server-0.1.7.dist-info/RECORD
