Metadata-Version: 2.1
Name: py-ampq-websocket-server
Version: 0.1.7
Summary: python websockets server using ampq
Home-page: https://github.com/knyazz/py-ampq-websocket-server
Author: Smirnov.EV
Author-email: knyazz@gmail.com
License: UNKNOWN
Platform: UNKNOWN
Classifier: Programming Language :: Python
Classifier: License :: OSI Approved :: MIT License
Classifier: Operating System :: OS Independent
Classifier: Topic :: Software Development :: Libraries :: Python Modules
Classifier: Intended Audience :: Developers
Classifier: Development Status :: 4 - Beta
Requires-Python: >=3.9
License-File: LICENSE
Requires-Dist: pika (>=1.2.0)
Requires-Dist: redis (>=2.9.1)
Requires-Dist: websockets (>=10.1)
